flask_ratelimit_simple/__init__.py
flask_ratelimit_simple/limiter.py
flask_ratelimit_simple-1.0.3.dist-info/licenses/LICENSE
flask_ratelimit_simple-1.0.3.dist-info/METADATA
flask_ratelimit_simple-1.0.3.dist-info/WHEEL
flask_ratelimit_simple-1.0.3.dist-info/top_level.txt
flask_ratelimit_simple-1.0.3.dist-info/RECORD
