Metadata-Version: 2.4
Name: flask-ratelimit-simple
Version: 1.0.3
Summary: Lightweight in-memory rate limiting for Flask
Home-page: https://github.com/wallmarkets/flask-ratelimit-simple
Author: wallmarkets Team
Author-email: team@wallmarkets.store
Project-URL: Bug Reports, https://github.com/wallmarkets/flask-ratelimit-simple/issues
Project-URL: Source, https://github.com/wallmarkets/flask-ratelimit-simple
Keywords: flask rate-limiting ratelimit throttle api-protection
Classifier: Development Status :: 5 - Production/Stable
Classifier: Intended Audience :: Developers
Classifier: License :: OSI Approved :: MIT License
Classifier: Programming Language :: Python :: 3
Classifier: Programming Language :: Python :: 3.7
Classifier: Programming Language :: Python :: 3.8
Classifier: Programming Language :: Python :: 3.9
Classifier: Programming Language :: Python :: 3.10
Classifier: Programming Language :: Python :: 3.11
Classifier: Framework :: Flask
Requires-Python: >=3.7
License-File: LICENSE
Requires-Dist: Flask>=2.0.0
Dynamic: author
Dynamic: author-email
Dynamic: classifier
Dynamic: description
Dynamic: description-content-type
Dynamic: home-page
Dynamic: keywords
Dynamic: license-file
Dynamic: project-url
Dynamic: requires-dist
Dynamic: requires-python
Dynamic: summary
